hardcoded/__init__.py
hardcoded/cli.py
hardcoded/git.py
hardcoded/logic.py
hardcoded-0.15.3.dist-info/METADATA
hardcoded-0.15.3.dist-info/WHEEL
hardcoded-0.15.3.dist-info/entry_points.txt
hardcoded-0.15.3.dist-info/RECORD
