Metadata-Version: 2.3
Name: hardcoded
Version: 0.15.3
Summary: For everything that you really should not be hardcoding.
License: LGPL-3.0-or-later
Author: moizuo
Author-email: no_spam@example.com
Requires-Python: >=3.9
Classifier: License :: OSI Approved :: GNU Lesser General Public License v3 or later (LGPLv3+)
Classifier: Programming Language :: Python :: 3
Classifier: Programming Language :: Python :: 3.9
Classifier: Programming Language :: Python :: 3.10
Classifier: Programming Language :: Python :: 3.11
Classifier: Programming Language :: Python :: 3.12
Classifier: Programming Language :: Python :: 3.13
Provides-Extra: encryption-without-pgp
Requires-Dist: Click (>=8.0.1)
Requires-Dist: cffi (>=1.15.1,<2.0.0) ; extra == "encryption-without-pgp"
Requires-Dist: cryptography (>=39.0.0) ; extra == "encryption-without-pgp"
Requires-Dist: python-dotenv (>=1.0.1)
Requires-Dist: python-gnupg
Requires-Dist: pyyaml
Project-URL: Repository, https://gitlab.com/zeroconfig/hardcoded
